crewmaster/__init__.py
crewmaster/core/__init__.py
crewmaster/core/pydantic/__init__.py
crewmaster/core/setup.py
crewmaster/core/ultra_ddd/__init__.py
crewmaster/core/ultra_ddd/emitter/__init__.py
crewmaster/core/ultra_ddd/emitter/emitter.py
crewmaster/core/ultra_ddd/emitter/emitter_explained.py
crewmaster/core/ultra_ddd/emitter/emitter_explained_test.py
crewmaster/core/ultra_ddd/emitter/emitter_test.py
crewmaster/core/ultra_ddd/use_case/__init__.py
crewmaster/core/ultra_ddd/use_case/use_case_base.py
crewmaster/core/ultra_result/__init__.py
crewmaster/core/ultra_result/either/__init__.py
crewmaster/core/ultra_result/either/either.py
crewmaster/core/ultra_result/either/left.py
crewmaster/core/ultra_result/either/right.py
crewmaster/features/__init__.py
crewmaster/features/agent/__init__.py
crewmaster/features/agent/agent_base.py
crewmaster/features/agent/agent_base_test.py
crewmaster/features/brain/__init__.py
crewmaster/features/brain/brain_base.py
crewmaster/features/brain/brain_base_test.py
crewmaster/features/brain/brain_types.py
crewmaster/features/brain/helpers/__init__.py
crewmaster/features/brain/helpers/convert_action_to_computation.py
crewmaster/features/brain/helpers/convert_action_to_computation_test.py
crewmaster/features/brain/helpers/convert_to_tool_call.py
crewmaster/features/brain/helpers/convert_to_tool_call_test.py
crewmaster/features/brain/helpers/convert_to_tool_message.py
crewmaster/features/brain/helpers/convert_to_tool_message_test.py
crewmaster/features/brain/helpers/ensure_dict.py
crewmaster/features/brain/helpers/ensure_dict_test.py
crewmaster/features/brain/helpers/is_response_structured.py
crewmaster/features/brain/helpers/is_response_structured_test.py
crewmaster/features/brain/helpers/is_skill_available.py
crewmaster/features/brain/helpers/is_skill_available_test.py
crewmaster/features/collaborator/__init__.py
crewmaster/features/collaborator/collaborator_base.py
crewmaster/features/collaborator/collaborator_base_test.py
crewmaster-0.1.21.dist-info/METADATA
crewmaster-0.1.21.dist-info/WHEEL
crewmaster-0.1.21.dist-info/entry_points.txt
crewmaster-0.1.21.dist-info/RECORD
